MAGOT2/__init__.py
MAGOT2/__main__.py
MAGOT2/lib.py
MAGOT2/tools.py
MAGOT2-2.0.1.dist-info/LICENSE
MAGOT2-2.0.1.dist-info/METADATA
MAGOT2-2.0.1.dist-info/WHEEL
MAGOT2-2.0.1.dist-info/entry_points.txt
MAGOT2-2.0.1.dist-info/top_level.txt
MAGOT2-2.0.1.dist-info/RECORD
