Metadata-Version: 2.1
Name: MAGOT2
Version: 2.0.1
Summary: "New, simpler toolkit for random common genomic analyses"
Home-page: UNKNOWN
License: UNKNOWN
Platform: UNKNOWN
Requires-Python: >=3.6
License-File: LICENSE
Requires-Dist: defopt
Requires-Dist: numpy
Requires-Dist: pandas
Requires-Dist: intervaltree
Requires-Dist: pysam
